framework/__init__.py
framework/data_types.py
framework/file_civa.py
framework/file_m2k.py
framework/post_proc.py
framework/pre_proc.py
imaging/__init__.py
imaging/bscan.py
imaging/cpwc.py
imaging/cumulative_tfm.py
imaging/saft.py
imaging/tfm.py
parameter_estimation/__init__.py
parameter_estimation/cl_estimators.py
parameter_estimation/intsurf_estimation.py
surface/__init__.py
surface/nonlinearopt.py
surface/surface.py
mini_auspex-1.5.11.dist-info/LICENSE
mini_auspex-1.5.11.dist-info/METADATA
mini_auspex-1.5.11.dist-info/WHEEL
mini_auspex-1.5.11.dist-info/top_level.txt
mini_auspex-1.5.11.dist-info/RECORD
