Metadata-Version: 2.1
Name: mini-auspex
Version: 1.5.11
Summary: Package for processing non-destructive ultrasound testing data
Home-page: http://auspex.xyz
Author: LASSIP-UTFPR
Author-email: giovanni@utfpr.edu.br
License-File: LICENSE
